MANIFEST.in
setup.cfg
setup.py
flask_jsondash/__init__.py
flask_jsondash/__init__.pyc
flask_jsondash/charts_builder.py
flask_jsondash/charts_builder.pyc
flask_jsondash/db.py
flask_jsondash/db.pyc
flask_jsondash/model_factories.py
flask_jsondash/model_factories.pyc
flask_jsondash/mongo_adapter.py
flask_jsondash/mongo_adapter.pyc
flask_jsondash/schema.py
flask_jsondash/schema.pyc
flask_jsondash/settings.py
flask_jsondash/settings.pyc
flask_jsondash.egg-info/PKG-INFO
flask_jsondash.egg-info/SOURCES.txt
flask_jsondash.egg-info/dependency_links.txt
flask_jsondash.egg-info/not-zip-safe
flask_jsondash.egg-info/requires.txt
flask_jsondash.egg-info/top_level.txt
flask_jsondash/__pycache__/__init__.cpython-35.pyc
flask_jsondash/__pycache__/__init__.cpython-36.pyc
flask_jsondash/__pycache__/charts_builder.cpython-35.pyc
flask_jsondash/__pycache__/charts_builder.cpython-36.pyc
flask_jsondash/__pycache__/db.cpython-35.pyc
flask_jsondash/__pycache__/db.cpython-36.pyc
flask_jsondash/__pycache__/model_factories.cpython-35.pyc
flask_jsondash/__pycache__/model_factories.cpython-36.pyc
flask_jsondash/__pycache__/mongo_adapter.cpython-35.pyc
flask_jsondash/__pycache__/mongo_adapter.cpython-36.pyc
flask_jsondash/__pycache__/schema.cpython-35.pyc
flask_jsondash/__pycache__/schema.cpython-36.pyc
flask_jsondash/__pycache__/settings.cpython-35.pyc
flask_jsondash/__pycache__/settings.cpython-36.pyc
flask_jsondash/data_utils/__init__.py
flask_jsondash/data_utils/__init__.pyc
flask_jsondash/data_utils/filetree.py
flask_jsondash/data_utils/filetree.pyc
flask_jsondash/data_utils/filetree_digraph.py
flask_jsondash/data_utils/filetree_digraph.pyc
flask_jsondash/data_utils/__pycache__/__init__.cpython-35.pyc
flask_jsondash/data_utils/__pycache__/__init__.cpython-36.pyc
flask_jsondash/data_utils/__pycache__/filetree.cpython-35.pyc
flask_jsondash/data_utils/__pycache__/filetree.cpython-36.pyc
flask_jsondash/data_utils/__pycache__/filetree_digraph.cpython-35.pyc
flask_jsondash/data_utils/__pycache__/filetree_digraph.cpython-36.pyc
flask_jsondash/static/.DS_Store
flask_jsondash/static/__init__.py
flask_jsondash/static/__init__.pyc
flask_jsondash/static/__pycache__/__init__.cpython-35.pyc
