Metadata-Version: 1.1
Name: flask-jsondash
Version: 6.2.3
Summary: Easily configurable, chart dashboards from any arbitrary API endpoint. JSON config only. Ready to go.
Home-page: https://github.com/christabor/flask_jsondash
Author: Chris Tabor
Author-email: dxdstudio@gmail.com
License: MIT
Platform: UNKNOWN
Classifier: Environment :: Web Environment
Classifier: Intended Audience :: Developers
Classifier: License :: OSI Approved :: BSD License
Classifier: Operating System :: OS Independent
Classifier: Programming Language :: Python :: 2.7
Classifier: Topic :: Internet :: WWW/HTTP :: Dynamic Content
Classifier: Topic :: Software Development :: Libraries :: Python Modules
